LICENSE
MANIFEST.in
README.md
requirements.txt
setup.cfg
setup.py
PyTDC.egg-info/PKG-INFO
PyTDC.egg-info/SOURCES.txt
PyTDC.egg-info/dependency_links.txt
PyTDC.egg-info/not-zip-safe
PyTDC.egg-info/requires.txt
PyTDC.egg-info/top_level.txt
pytdc.egg-info/PKG-INFO
pytdc.egg-info/SOURCES.txt
pytdc.egg-info/dependency_links.txt
pytdc.egg-info/not-zip-safe
pytdc.egg-info/requires.txt
pytdc.egg-info/top_level.txt
tdc/__init__.py
tdc/base_dataset.py
tdc/benchmark_deprecated.py
tdc/evaluator.py
tdc/metadata.py
tdc/oracles.py
tdc/version.py
tdc/benchmark_group/__init__.py
tdc/benchmark_group/admet_group.py
tdc/benchmark_group/base_group.py
tdc/benchmark_group/counterfactual_group.py
tdc/benchmark_group/docking_group.py
tdc/benchmark_group/drugcombo_group.py
tdc/benchmark_group/dti_dg_group.py
tdc/benchmark_group/geneperturb_group.py
tdc/benchmark_group/protein_peptide_group.py
tdc/benchmark_group/scdti_group.py
tdc/benchmark_group/tcrepitope_group.py
tdc/chem_utils/__init__.py
tdc/chem_utils/evaluator.py
tdc/chem_utils/featurize/__init__.py
tdc/chem_utils/featurize/_smartsPatts.py
tdc/chem_utils/featurize/_smiles2pubchem.py
tdc/chem_utils/featurize/_xyz2mol.py
tdc/chem_utils/featurize/molconvert.py
tdc/chem_utils/oracle/__init__.py
tdc/chem_utils/oracle/docking.py
tdc/chem_utils/oracle/filter.py
tdc/chem_utils/oracle/oracle.py
tdc/dataset_configs/__init__.py
tdc/dataset_configs/brown_mdm2_ace2_12ca5_config.py
tdc/dataset_configs/cellxgene_config.py
tdc/dataset_configs/config.py
tdc/dataset_configs/config_map.py
tdc/dataset_configs/opentargets_dti.py
tdc/dataset_configs/scperturb_config.py
tdc/feature_generators/__init__.py
tdc/feature_generators/anndata_to_dataframe.py
tdc/feature_generators/base.py
tdc/feature_generators/cellxgene_generator.py
tdc/feature_generators/data_feature_generator.py
tdc/feature_generators/protein_feature_generator.py
tdc/feature_generators/resource.py
tdc/generation/__init__.py
tdc/generation/bi_generation_dataset.py
tdc/generation/generation_dataset.py
tdc/generation/ligandmolgen.py
tdc/generation/molgen.py
tdc/generation/reaction.py
tdc/generation/retrosyn.py
tdc/generation/sbdd.py
tdc/model_server/__init__.py
tdc/model_server/tdc_hf.py
tdc/model_server/models/__init__.py
tdc/model_server/models/scgpt.py
tdc/model_server/models/scvi.py
tdc/model_server/tokenizers/__init__.py
