Metadata-Version: 2.1
Name: pytdc
Version: 1.1.15
Summary: Therapeutics Commons
Home-page: https://github.com/mims-harvard/TDC
Author: PyTDC Team
Author-email: amva13@alum.mit.edu
License: MIT
License-File: LICENSE
Requires-Dist: accelerate==0.33.0
Requires-Dist: dataclasses<1.0,>=0.6
Requires-Dist: datasets<2.20.0
Requires-Dist: evaluate==0.4.2
Requires-Dist: fuzzywuzzy<1.0,>=0.18.0
Requires-Dist: huggingface_hub<1.0,>=0.20.3
Requires-Dist: numpy<2.0.0,>=1.26.4
Requires-Dist: openpyxl<4.0.0,>=3.0.10
Requires-Dist: pandas<3.0.0,>=2.1.4
Requires-Dist: requests<3.0.0,>=2.31.0
Requires-Dist: scikit-learn>=1.2.2
Requires-Dist: seaborn<1.0.0,>=0.12.2
Requires-Dist: tqdm<5.0.0,>=4.65.0
Requires-Dist: transformers<4.51.0,>=4.43.0
Requires-Dist: cellxgene-census==1.15.0
Requires-Dist: gget<1.0.0,>=0.28.4
Requires-Dist: pydantic<3.0.0,>=2.6.3
Requires-Dist: rdkit<2024.3.1,>=2023.9.5
Requires-Dist: tiledbsoma<2.0.0,>=1.7.2
